{
    "classifiers": [
        "Intended Audience :: Developers",
        "Intended Audience :: Science/Research",
        "License :: OSI Approved :: MIT License",
        "Natural Language :: English",
        "Operating System :: Unix",
        "Operating System :: POSIX",
        "Programming Language :: Python :: 2 :: Only",
        "Topic :: Utilities"
    ],
    "entry_points": {
        "console_scripts": [
            "toil_pindel=toil_pindel.cli:main"
        ]
    },
    "setup_requires": [
        "pytest-runner==2.11.1"
    ],
    "install_requires": [
        "toil_container==1.1.6",
        "more-itertools<6.0.0"
    ],
    "extras_require": {
        "test": [
            "pytest==3.7.4",
            "coverage==4.4.2",
            "pydocstyle==2.1.1",
            "pytest-cov==2.5.1",
            "pytest-env==0.6.2",
            "pytest-sugar==0.9.1",
            "pylint==1.8.1"
        ]
    },
    "author": "Juan S. Medina",
    "keywords": [],
    "license": "BSD",
    "name": "toil_pindel",
    "test_suite": "tests",
    "long_description": "📘 learn more on `GitHub <https://github.com/papaemmelab/toil_pindel>`_!",
    "description": "A toil wrapper for cgp pindel.",
    "url": "https://github.com/papaemmelab/toil_pindel"
}
